pyllelize/__init__.py
pyllelize/process.py
pyllelize/threads.py
pyllelize-0.2.1.dist-info/METADATA
pyllelize-0.2.1.dist-info/WHEEL
pyllelize-0.2.1.dist-info/RECORD
