Metadata-Version: 2.1
Name: pyllelize
Version: 0.2.1
Summary: A library offers streamlined utilities to simplify the parallelization of Python functions
Home-page: https://github.com/jsaied99/pyllelize
License: MIT
Author: Jamal S
Author-email: jsaied99@gmail.com
Requires-Python: >=3.9,<4.0
Classifier: License :: OSI Approved :: MIT License
Classifier: Programming Language :: Python :: 3
Classifier: Programming Language :: Python :: 3.9
Classifier: Programming Language :: Python :: 3.10
Classifier: Programming Language :: Python :: 3.11
Project-URL: Repository, https://github.com/jsaied99/pyllelize
